aioevents/__init__.py
aioevents_ng-0.0.9.dist-info/LICENSE
aioevents_ng-0.0.9.dist-info/METADATA
aioevents_ng-0.0.9.dist-info/WHEEL
aioevents_ng-0.0.9.dist-info/top_level.txt
aioevents_ng-0.0.9.dist-info/RECORD
