Metadata-Version: 2.1
Name: aioevents-ng
Version: 0.0.9
Summary: A simple library for managing events through an asynchronous queue
Home-page: https://github.com/mpyatishev/aioevents
Author: Maxim Pyatishev
Author-email: mpyatishev@gmail.com
License: UNKNOWN
Platform: UNKNOWN
Classifier: License :: OSI Approved :: Apache Software License
Classifier: Intended Audience :: Developers
Classifier: Programming Language :: Python
Classifier: Programming Language :: Python :: 3
Classifier: Programming Language :: Python :: 3.7
Classifier: Topic :: Software Development :: Libraries
Classifier: Framework :: AsyncIO
Requires-Python: >=3.7
Requires-Dist: aiorecycle (>="0.0.2")
